{"name":"Doubtful Kasm Registry","workspacecount":2,"icon":"https://avatars.githubusercontent.com/u/23531986?v=4","description":"A mash of custom images","list_url":"https://doubtfulturnip.github.io/doubtful-kasm-registry/","contact_url":"https://github.com/DoubtfulTurnip/","modified":1684290032486,"workspaces":[{"description":"Chromium is a free and open-source browser, primarily developed and maintained by Google.","docker_registry":"https://index.docker.io/v1/","image_src":"chromium.png","name":"kasmweb/chromium:develop","run_config":{"hostname":"kasm"},"exec_config":{"go":{"cmd":"bash -c '/dockerstartup/custom_startup.sh --go --url \"$KASM_URL\"'"},"assign":{"cmd":"bash -c '/dockerstartup/custom_startup.sh --assign --url \"$KASM_URL\"'"}},"categories":["Browser"],"friendly_name":"Chromium","architecture":["amd64","arm64"],"compatibility":["1.13.x"],"uncompressed_size_mb":2170,"sha":"c47aba1be459ed66fc58bca2fb6a3c797dd26ca1"},{"friendly_name":"LogonTracer","image_src":"logontracer.png","description":"LogonTracer is a tool to investigate malicious logon by visualizing and analyzing Windows Active Directory event logs","name":"bukshee/logontracer-kasm:latest","run_config":{"hostname":"kasm"},"cores":2,"memory":2768,"gpu_count":0,"cpu_allocation_method":"Inherit","docker_registry":"https://index.docker.io/v1/","categories":["Security"],"compatibility":["1.13.x"],"require_gpu":false,"enabled":true,"image_type":"Container","architecture":["amd64"],"sha":"b2842a74722264929467d3e0d370b720eb6223f2"}]}